tiny_ldap_manager/__init__.py
tiny_ldap_manager/_version.py
tiny_ldap_manager/delete_bulk.py
tiny_ldap_manager/tiny_ldap_manager.py
tiny_ldap_manager/tlmgr_core.py
tiny_ldap_manager/tlmgr_csv.py
tiny_ldap_manager/tlmgr_modify.py
tiny_ldap_manager-0.2.1.data/scripts/_version.py
tiny_ldap_manager-0.2.1.dist-info/LICENSE
tiny_ldap_manager-0.2.1.dist-info/METADATA
tiny_ldap_manager-0.2.1.dist-info/WHEEL
tiny_ldap_manager-0.2.1.dist-info/entry_points.txt
tiny_ldap_manager-0.2.1.dist-info/top_level.txt
tiny_ldap_manager-0.2.1.dist-info/RECORD
