Metadata-Version: 2.1
Name: tiny-ldap-manager
Version: 0.2.1
Summary: Easily perform several LDAP operations
Home-page: https://github.com/tuxedoar/tiny-ldap-manager
Author: tuxedoar
Author-email: tuxedoar@gmail.com
License: GPLv3
Platform: UNKNOWN
Classifier: Programming Language :: Python :: 3 :: Only
Classifier: Programming Language :: Python :: 3.7
Classifier: License :: OSI Approved :: GNU General Public License v3 (GPLv3)
Classifier: Operating System :: OS Independent
Classifier: Intended Audience :: System Administrators
Classifier: Environment :: Console
Classifier: Topic :: System :: Systems Administration :: Authentication/Directory :: LDAP
Requires-Python: >=3.7
Requires-Dist: python-ldap
